noscrapy/__init__.py
noscrapy/selectors/__init__.py
noscrapy/selectors/base.py
noscrapy/selectors/html.py
noscrapy/selectors/link.py
noscrapy/selectors/text.py
noscrapy/utils/__init__.py
noscrapy/utils/declarative.py
noscrapy/utils/pyquery.py
noscrapy-0.0.2.dist-info/DESCRIPTION.rst
noscrapy-0.0.2.dist-info/METADATA
noscrapy-0.0.2.dist-info/RECORD
noscrapy-0.0.2.dist-info/WHEEL
noscrapy-0.0.2.dist-info/metadata.json
noscrapy-0.0.2.dist-info/top_level.txt
