Metadata-Version: 2.0
Name: noscrapy
Version: 0.0.2
Summary: Python port attempt of web-scraper-chrome-extension.
Home-page: https://github.com/katakumpo/noscrapy
Author: Mathias Seidler
Author-email: seishin@gmail.com
License: MIT
Platform: UNKNOWN
Classifier: Development Status :: 3 - Alpha
Classifier: License :: OSI Approved :: MIT License
Classifier: Programming Language :: Python
Classifier: Programming Language :: Python :: 3
Classifier: Programming Language :: Python :: 3.5
Classifier: Topic :: Utilities
Requires-Dist: pyquery (>=1.2.11)
